{
    "hpOffset": -10,
    "maximumLevel": 15,
    "hpPerLevel": 2,
    "healOnLevelUp": true,
    "resetOnDeath": false,
    "xpTargetFunction": {
        "terms": [
            {
                "exponent": 0,
                "coefficient": 1000
            },
            {
                "exponent": 1,
                "coefficient": 500
            }
        ]
    },
    "xpPenaltyFunction": {
        "terms": [
            {
                "exponent": 0,
                "coefficient": 250
            },
            {
                "exponent": 1,
                "coefficient": 120
            }
        ]
    },
    "levelPenaltyFunction": {
        "terms": []
    },
    "primaryXpValues": {
        "animal": 20,
        "mob": 50
    }
}
